SploitfunLinuxX86ExploitKaifaXilieJiaocheng/README.md
SploitfunLinuxX86ExploitKaifaXilieJiaocheng/__init__.py
SploitfunLinuxX86ExploitKaifaXilieJiaocheng/__main__.py
SploitfunLinuxX86ExploitKaifaXilieJiaocheng/file.epub
SploitfunLinuxX86ExploitKaifaXilieJiaocheng/index.html
SploitfunLinuxX86ExploitKaifaXilieJiaocheng/css/__init__.py
SploitfunLinuxX86ExploitKaifaXilieJiaocheng/css/annotations.css
SploitfunLinuxX86ExploitKaifaXilieJiaocheng/css/main.css
SploitfunLinuxX86ExploitKaifaXilieJiaocheng/css/normalize.css
SploitfunLinuxX86ExploitKaifaXilieJiaocheng/css/popup.css
SploitfunLinuxX86ExploitKaifaXilieJiaocheng/font/__init__.py
SploitfunLinuxX86ExploitKaifaXilieJiaocheng/font/fontello.eot
SploitfunLinuxX86ExploitKaifaXilieJiaocheng/font/fontello.svg
SploitfunLinuxX86ExploitKaifaXilieJiaocheng/font/fontello.ttf
SploitfunLinuxX86ExploitKaifaXilieJiaocheng/font/fontello.woff
SploitfunLinuxX86ExploitKaifaXilieJiaocheng/img/__init__.py
SploitfunLinuxX86ExploitKaifaXilieJiaocheng/img/annotator-glyph-sprite.png
SploitfunLinuxX86ExploitKaifaXilieJiaocheng/img/annotator-icon-sprite.png
SploitfunLinuxX86ExploitKaifaXilieJiaocheng/img/apple-touch-icon.png
SploitfunLinuxX86ExploitKaifaXilieJiaocheng/img/cancelfullscreen.png
SploitfunLinuxX86ExploitKaifaXilieJiaocheng/img/close.png
SploitfunLinuxX86ExploitKaifaXilieJiaocheng/img/fullscreen.png
SploitfunLinuxX86ExploitKaifaXilieJiaocheng/img/loader.gif
SploitfunLinuxX86ExploitKaifaXilieJiaocheng/img/menu-icon.png
SploitfunLinuxX86ExploitKaifaXilieJiaocheng/img/save.png
SploitfunLinuxX86ExploitKaifaXilieJiaocheng/img/saved.png
SploitfunLinuxX86ExploitKaifaXilieJiaocheng/img/settings-s.png
SploitfunLinuxX86ExploitKaifaXilieJiaocheng/img/settings.png
SploitfunLinuxX86ExploitKaifaXilieJiaocheng/img/star.png
SploitfunLinuxX86ExploitKaifaXilieJiaocheng/js/__init__.py
SploitfunLinuxX86ExploitKaifaXilieJiaocheng/js/epub.js
SploitfunLinuxX86ExploitKaifaXilieJiaocheng/js/epub.min.js
sploitfun_linux_x86_exploit_kaifa_xilie_jiaocheng-2024.3.2.0.dist-info/METADATA
sploitfun_linux_x86_exploit_kaifa_xilie_jiaocheng-2024.3.2.0.dist-info/WHEEL
sploitfun_linux_x86_exploit_kaifa_xilie_jiaocheng-2024.3.2.0.dist-info/entry_points.txt
sploitfun_linux_x86_exploit_kaifa_xilie_jiaocheng-2024.3.2.0.dist-info/top_level.txt
sploitfun_linux_x86_exploit_kaifa_xilie_jiaocheng-2024.3.2.0.dist-info/RECORD
